mtclass_ensemble/__init__.py
mtclass_ensemble/ensemble.py
mtclass_ensemble/extract_genotypes.py
mtclass_ensemble/gwas_variant_colocalization.py
mtclass_ensemble-0.1.0.dist-info/licenses/LICENSE.txt
mtclass_ensemble-0.1.0.dist-info/METADATA
mtclass_ensemble-0.1.0.dist-info/WHEEL
mtclass_ensemble-0.1.0.dist-info/top_level.txt
mtclass_ensemble-0.1.0.dist-info/RECORD
