Metadata-Version: 2.4
Name: mtclass_ensemble
Version: 0.1.0
Summary: MTClass ensemble algorithm for identifying multi-phenotype cis-eQTLs
Home-page: https://github.com/ronnieli0114/MTClass
Author: Ronnie Li
Author-email: ronnieli0114@gmail.com
License: MIT
Classifier: License :: OSI Approved :: MIT License
Classifier: Programming Language :: Python :: 3.12
Classifier: Operating System :: OS Independent
Requires-Python: >=3.12
License-File: LICENSE.txt
Requires-Dist: scikit-learn>=1.5.2
Requires-Dist: pandas>=2.2.1
Requires-Dist: numpy>=1.26.4
Requires-Dist: pyarrow>=17.0.0
Provides-Extra: dev
Requires-Dist: twine>=6.0.1; extra == "dev"
Dynamic: author
Dynamic: author-email
Dynamic: classifier
Dynamic: description
Dynamic: description-content-type
Dynamic: home-page
Dynamic: license
Dynamic: license-file
Dynamic: provides-extra
Dynamic: requires-dist
Dynamic: requires-python
Dynamic: summary
